macsesh/__init__.py
macsesh/injected_adapter.py
macsesh/keychain.py
macsesh/secure_transport_adapter.py
macsesh/session.py
macsesh/simple_adapter.py
macsesh/util.py
macsesh/version.py
MacSesh-0.3.1.dist-info/LICENSE.txt
MacSesh-0.3.1.dist-info/METADATA
MacSesh-0.3.1.dist-info/WHEEL
MacSesh-0.3.1.dist-info/top_level.txt
MacSesh-0.3.1.dist-info/RECORD
