Metadata-Version: 2.1
Name: MacSesh
Version: 0.3.1
Summary: Tools for letting the macOS Keychain verify certs for python requests
Home-page: https://github.com/sheagcraig/MacSesh
Author: Shea G. Craig
Author-email: sheagcraig@gmail.com
License: GPLv3
Platform: UNKNOWN
Classifier: Development Status :: 3 - Alpha
Classifier: Environment :: MacOS X
Classifier: Environment :: MacOS X :: Cocoa
Classifier: Intended Audience :: Developers
Classifier: Intended Audience :: Information Technology
Classifier: Intended Audience :: System Administrators
Classifier: License :: OSI Approved :: Apache Software License
Classifier: Operating System :: MacOS
Classifier: Operating System :: MacOS :: MacOS X
Classifier: Programming Language :: Python :: 3 :: Only
Requires-Python: >=3.6
License-File: LICENSE.txt
Requires-Dist: requests
Requires-Dist: pyobjc-framework-SecurityFoundation
Requires-Dist: six
